README.txt
setup.cfg
setup.py
conML/__init__.py
conML.egg-info/PKG-INFO
conML.egg-info/SOURCES.txt
conML.egg-info/dependency_links.txt
conML.egg-info/requires.txt
conML.egg-info/top_level.txt
conML/controller/__init__.py
conML/controller/api.py
conML/domain/__init__.py
conML/domain/knowledge.py
conML/domain/preprocessing.py
conML/domain/construction/__init__.py
conML/domain/construction/construction.py
conML/domain/deconstruction/__init__.py
conML/domain/deconstruction/abstract.py
conML/domain/deconstruction/complete.py
conML/domain/deconstruction/deconstruction.py
conML/domain/deconstruction/t_sigma.py
conML/domain/deconstruction/z_sigma.py
conML/domain/reconstruction/__init__.py
conML/domain/reconstruction/reconstruction.py
conML/domain/reconstruction/selection.py
conML/ports/__init__.py
conML/ports/ckmeans_adapter.py
conML/ports/krippendorff_adapter.py
conML/ports/ml_adapter.py
conML/ports/source_adapter.py
conML/shared/__init__.py
conML/shared/errors.py
conML/shared/logger.py
conML/shared/parameter.py
conML/shared/request.py
conML/shared/settings.py
conML/static/logging.ini
conML/static/settings.ini
conML/static/toyset.csv
conML/usecases/__init__.py
conML/usecases/command.py
conML/usecases/query.py
conML/usecases/usecase.py