Metadata-Version: 2.1
Name: conML
Version: 0.31
Summary: constructivist machine learning
Home-page: UNKNOWN
Author: Dmitrij Denisenko
License: MIT
Platform: UNKNOWN
